rugpi/__init__.py
rugpi-0.0.0.dist-info/METADATA
rugpi-0.0.0.dist-info/WHEEL
rugpi-0.0.0.dist-info/RECORD
