Metadata-Version: 2.1
Name: rugpi
Version: 0.0.0
Summary: This package has been reserved for Rugpi.
Author: Silitics GmbH
Author-email: info@silitics.com
Requires-Python: >=3.12,<4.0
Classifier: Programming Language :: Python :: 3
Classifier: Programming Language :: Python :: 3.12
